marktex/__init__.py
marktex/api.py
marktex/cli.py
marktex/markenv.tex
marktex/util.py
marktex/example/all_example.md
marktex/example/code_example.md
marktex/example/example.md
marktex/example/exampleimage.png
marktex/example/footnote_example.md
marktex/example/formula_example.md
marktex/example/image_example.md
marktex/example/itemize_example.md
marktex/example/normal_example.md
marktex/example/quote_example.md
marktex/example/show.md
marktex/example/table_example.md
marktex/example/texfile.tex
marktex/example/yaml_head.md
marktex/markast/__init__.py
marktex/markast/base.py
marktex/markast/environments.py
marktex/markast/lines.py
marktex/markast/tokens.py
marktex/markfmt/__init__.py
marktex/texparser/__init__.py
marktex/texparser/base.py
marktex/texparser/sign_to_tex.txt
marktex/texparser/texparser.py
marktex/texparser/texunit.py
tests/__init__.py
marktex-0.9.8.dist-info/METADATA
marktex-0.9.8.dist-info/WHEEL
marktex-0.9.8.dist-info/entry_points.txt
marktex-0.9.8.dist-info/top_level.txt
marktex-0.9.8.dist-info/RECORD
