Metadata-Version: 2.1
Name: marktex
Version: 0.9.8
Summary: convert markdown 2 latex code perfactly,support Chinese Language
Home-page: https://github.com/sailist/MarkTex
Author: hzYang
Author-email: sailist@outlook.com
License: MIT
Keywords: markdown latex convert
Platform: UNKNOWN
Classifier: Development Status :: 3 - Alpha
Classifier: Intended Audience :: Developers
Classifier: Topic :: Software Development :: Build Tools
Classifier: License :: OSI Approved :: MIT License
Classifier: Programming Language :: Python :: 3.5
Classifier: Programming Language :: Python :: 3.6
Requires-Dist: pylatex
Requires-Dist: matplotlib
Requires-Dist: requests
